keyrings/__init__.py
keyrings/codeartifact.py
keyrings_codeartifact-2.1.2.dist-info/licenses/LICENSE
keyrings_codeartifact-2.1.2.dist-info/METADATA
keyrings_codeartifact-2.1.2.dist-info/WHEEL
keyrings_codeartifact-2.1.2.dist-info/entry_points.txt
keyrings_codeartifact-2.1.2.dist-info/top_level.txt
keyrings_codeartifact-2.1.2.dist-info/RECORD
