Metadata-Version: 2.4
Name: keyrings.codeartifact
Version: 2.1.2
Summary: Automatically retrieve credentials for AWS CodeArtifact.
Author-email: "Joshua M. Keyes" <joshua.michael.keyes@gmail.com>
Project-URL: Homepage, https://github.com/jmkeyes/keyrings.codeartifact
Project-URL: Issues, https://github.com/jmkeyes/keyrings.codeartifact/issues
Project-URL: Repository, https://github.com/jmkeyes/keyrings.codeartifact.git
Keywords: aws,codeartifact,keyring
Classifier: Development Status :: 4 - Beta
Classifier: Intended Audience :: Developers
Classifier: Programming Language :: Python :: 3
Classifier: Programming Language :: Python :: 3 :: Only
Requires-Python: >=3.9
License-File: LICENSE
Requires-Dist: keyring~=25.6
Requires-Dist: boto3~=1.39
Provides-Extra: dev
Requires-Dist: flake8; extra == "dev"
Requires-Dist: black; extra == "dev"
Provides-Extra: test
Requires-Dist: pytest>=6; extra == "test"
Requires-Dist: pytest-cov; extra == "test"
Dynamic: license-file
